pymagnitude/__init__.py
pymagnitude/converter.py
pymagnitude/converter_shared.py
pymagnitude/third_party/__init__.py
pymagnitude/third_party/repoze/__init__.py
pymagnitude/third_party/repoze/lru/__init__.py
pymagnitude/third_party/repoze/lru/tests.py
pymagnitude_lite-0.1.143.dist-info/LICENSE.txt
pymagnitude_lite-0.1.143.dist-info/METADATA
pymagnitude_lite-0.1.143.dist-info/WHEEL
pymagnitude_lite-0.1.143.dist-info/top_level.txt
pymagnitude_lite-0.1.143.dist-info/RECORD
